hawk_tuah/__init__.py
hawk_tuah-0.1.dist-info/METADATA
hawk_tuah-0.1.dist-info/WHEEL
hawk_tuah-0.1.dist-info/top_level.txt
hawk_tuah-0.1.dist-info/RECORD
